{
  "KTJWBTN1DA": {
    "22": {
      "LUK1:11-14": [
        157.944,
        163.194,
        176.014,
        180.974,
        193.364
      ],
      "LUK1:18": [
        238.226,
        249.366
      ],
      "LUK1:19-20": [
        249.366,
        260.446,
        273.286
      ],
      "LUK1:22-24": [
        287.147,
        300.637,
        310.607,
        319.387
      ],
      "LUK1:26": [
        333.358,
        352.858
      ],
      "LUK1:30-33": [
        381.909,
        387.709,
        402.199,
        407.859,
        414.5
      ],
      "LUK1:34-35": [
        414.5,
        433.76,
        444.65
      ],
      "LUK1:38": [
        462.751,
        476.161
      ],
      "LUK1:39-41": [
        476.161,
        482.711,
        495.892,
        505.522
      ],
      "LUK1:5-7": [
        89.472,
        99.712,
        107.102,
        117.743
      ],
      "LUK1:56": [
        636.255,
        648.035
      ],
      "LUK1:57": [
        648.035,
        656.965
      ],
      "LUK1:62-64": [
        682.636,
        694.926,
        703.836,
        714.977
      ],
      "LUK1:8": [
        117.743,
        140.373
      ]
    },
    "23": {
      "LUK2:1": [
        3.0,
        27.591
      ],
      "LUK2:12-14": [
        185.795,
        195.116,
        212.676,
        231.177
      ],
      "LUK2:15-17": [
        231.177,
        239.807,
        244.527,
        249.997
      ],
      "LUK2:4-5": [
        45.611,
        90.473,
        113.773
      ],
      "LUK2:6-7": [
        113.773,
        119.933,
        133.574
      ],
      "LUK2:8-11": [
        133.574,
        143.664,
        161.775,
        177.125,
        185.795
      ],
      "MAT1:18-19": [
        178.774,
        192.885,
        213.797
      ],
      "MAT1:20-21": [
        213.797,
        230.968,
        241.069
      ],
      "MAT1:24-25": [
        258.19,
        265.541,
        265.541
      ],
      "MAT2:1-2": [
        3.21,
        30.601,
        45.691
      ],
      "MAT2:11": [
        141.573,
        162.983
      ],
      "MAT2:9-10": [
        117.782,
        136.682,
        141.573
      ]
    }
  }
}