{
  "MARDPIO1DA": {
    "1": {
      "GEN1:1-2": [
        8.06,
        12.7,
        22.96
      ],
      "GEN1:10-11": [
        83.56,
        94.46,
        108.72
      ],
      "GEN1:14-18": [
        132.4,
        145.4,
        153.6,
        166.62,
        166.62,
        181.72
      ],
      "GEN1:20": [
        186.64,
        196.2
      ],
      "GEN1:22": [
        215.6,
        227.0
      ],
      "GEN1:24-25": [
        232.14,
        244.02,
        257.56
      ],
      "GEN1:26-27": [
        257.56,
        277.46,
        290.7
      ],
      "GEN1:27-28": [
        277.46,
        290.7,
        309.3
      ],
      "GEN1:3-5": [
        22.96,
        26.9,
        34.16,
        45.6
      ],
      "GEN1:6-8": [
        45.6,
        53.42,
        63.38,
        72.98
      ],
      "GEN1:9-10": [
        72.98,
        83.56,
        94.46
      ],
      "GEN2:1-3": [
        2.7,
        13.4,
        26.86,
        42.5
      ],
      "GEN2:16": [
        177.36,
        186.02
      ],
      "GEN2:18": [
        199.02,
        209.16
      ],
      "GEN2:21-22": [
        243.84,
        259.0,
        266.0
      ],
      "GEN2:23-24": [
        266.0,
        284.0,
        291.88
      ],
      "GEN2:7-8": [
        82.0,
        97.0,
        106.22
      ],
      "GEN2:9": [
        106.22,
        126.46
      ]
    },
    "2": {
      "GEN2:25": [
        291.88,
        291.88
      ],
      "GEN3:1": [
        5.04,
        19.94
      ],
      "GEN3:11-13": [
        127.18,
        139.16,
        148.2,
        159.68
      ],
      "GEN3:14-15": [
        159.68,
        177.0,
        190.04
      ],
      "GEN3:16": [
        190.04,
        204.48
      ],
      "GEN3:17-21": [
        204.48,
        228.26,
        236.78,
        256.74,
        265.42,
        274.06
      ],
      "GEN3:2-3": [
        19.94,
        24.84,
        36.44
      ],
      "GEN3:22-24": [
        274.06,
        296.0,
        307.76,
        307.76
      ],
      "GEN3:4-5": [
        36.44,
        40.12,
        53.62
      ],
      "GEN3:6": [
        53.62,
        76.7
      ],
      "GEN3:7": [
        76.7,
        91.22
      ],
      "GEN3:8-10": [
        91.22,
        111.2,
        116.64,
        127.18
      ]
    },
    "3": {
      "GEN6:1": [
        6.08,
        10.7
      ],
      "GEN6:13-14": [
        132.32,
        149.8,
        161.14
      ],
      "GEN6:15-19": [
        161.14,
        173.04,
        187.36,
        202.22,
        213.52,
        226.66
      ],
      "GEN6:21": [
        240.8,
        250.74
      ],
      "GEN6:22": [
        250.74,
        250.74
      ],
      "GEN6:5-7": [
        48.7,
        62.52,
        71.48,
        89.58
      ],
      "GEN6:8": [
        89.58,
        97.22
      ],
      "GEN7:1": [
        5.02,
        17.1
      ],
      "GEN7:13-16": [
        123.16,
        135.48,
        159.5,
        169.48,
        180.76
      ],
      "GEN7:17": [
        180.76,
        189.7
      ],
      "GEN7:20": [
        209.64,
        216.4
      ],
      "GEN7:23": [
        235.74,
        257.16
      ],
      "GEN7:4": [
        40.42,
        52.88
      ],
      "GEN7:7": [
        62.4,
        71.2
      ],
      "GEN8:12-14": [
        114.42,
        123.84,
        141.7,
        146.82
      ],
      "GEN8:14-19": [
        141.7,
        146.82,
        148.5,
        155.94,
        175.92,
        183.36,
        196.18
      ],
      "GEN8:20": [
        196.18,
        208.7
      ],
      "GEN8:21-22": [
        208.7,
        228.9,
        228.9
      ],
      "GEN8:3-4": [
        28.6,
        37.32,
        42.78
      ],
      "GEN8:6-7": [
        51.52,
        56.88,
        65.34
      ],
      "GEN8:8-11": [
        65.34,
        75.56,
        93.22,
        99.84,
        114.42
      ],
      "GEN9:1": [
        5.7,
        15.58
      ],
      "GEN9:11-17": [
        115.32,
        131.8,
        145.5,
        154.82,
        161.56,
        180.64,
        194.14,
        208.44
      ]
    },
    "4": {
      "GEN11:1-2": [
        6.68,
        13.64,
        22.4
      ],
      "GEN11:4": [
        34.36,
        56.0
      ],
      "GEN11:5-6": [
        56.0,
        63.14,
        79.08
      ],
      "GEN11:7-9": [
        79.08,
        88.42,
        95.98,
        114.66
      ],
      "GEN12:1-3": [
        8.44,
        17.94,
        29.38,
        44.76
      ],
      "GEN12:4-5": [
        44.76,
        58.1,
        78.2
      ],
      "GEN12:6-7": [
        78.2,
        89.46,
        105.14
      ],
      "GEN14:18-20": [
        250.56,
        261.8,
        271.04,
        280.88
      ],
      "GEN15:18": [
        195.86,
        204.94
      ],
      "GEN15:2-6": [
        21.82,
        34.02,
        41.68,
        53.38,
        63.9,
        71.72
      ]
    },
    "5": {
      "GEN16:1-3": [
        6.1,
        17.0,
        32.7,
        45.72
      ],
      "GEN16:15-16": [
        186.14,
        197.16,
        197.16
      ],
      "GEN17:1": [
        6.72,
        19.82
      ],
      "GEN17:1-10": [
        6.72,
        19.82,
        31.64,
        37.36,
        44.14,
        56.24,
        66.06,
        80.98,
        92.2,
        107.56,
        118.04
      ],
      "GEN17:15-16": [
        165.72,
        177.48,
        191.5
      ],
      "GEN17:18-21": [
        208.68,
        213.68,
        230.94,
        252.26,
        261.4
      ],
      "GEN17:25": [
        293.46,
        299.3
      ],
      "GEN17:26-27": [
        299.3,
        305.42,
        305.42
      ],
      "GEN22:1-3": [
        9.58,
        20.06,
        36.16,
        57.32
      ],
      "GEN22:13": [
        170.0,
        187.44
      ],
      "GEN22:15-18": [
        201.78,
        207.96,
        221.16,
        239.0,
        247.84
      ],
      "GEN22:6-8": [
        78.44,
        91.62,
        105.1,
        115.28
      ],
      "GEN22:9-12": [
        115.28,
        133.22,
        140.48,
        151.34,
        170.0
      ]
    }
  },
  "warnings": {
    "MARDPIO1DA": {
      "1": {
        "GEN1:14-18": {
          "details": "verse 18 missing, timestamps repeated",
          "missing_verses": [
            18
          ],
          "type": "partial"
        }
      }
    }
  }
}