{
  "language": "tel",
  "canon": "OT",
  "category": "with-timecode",
  "original_category": "with-timecode",
  "distinct_id": "TELDPI",
  "filesets": {
    "audio": {
      "TELDPIO1DA": {
        "status": "available",
        "files": [
          "PSA/PSA_117_TELDPIO1DA.mp3"
        ]
      }
    },
    "text": {
      "TELDPIO": {
        "status": "available",
        "files": [
          "PSA/PSA_117_TELDPIO_ET.txt"
        ]
      }
    },
    "timing": {
      "TELDPIO1DA_timing": {
        "status": "available",
        "files": [
          "PSA/PSA_117_TELDPIO1DA_timing.json"
        ]
      }
    }
  }
}